fantomatic_engine/__init__.py
fantomatic_engine/edit_segments.py
fantomatic_engine/run_game.py
fantomatic_engine/game/__init__.py
fantomatic_engine/game/action_keys_listener.py
fantomatic_engine/game/config.py
fantomatic_engine/game/door.py
fantomatic_engine/game/game.py
fantomatic_engine/game/interactable.py
fantomatic_engine/game/interactions_manager.py
fantomatic_engine/game/lang.py
fantomatic_engine/game/scene.py
fantomatic_engine/game/skip_cinematic_listener.py
fantomatic_engine/game/sound_player.py
fantomatic_engine/game/sprites/__init__.py
fantomatic_engine/game/sprites/bot.py
fantomatic_engine/game/sprites/character.py
fantomatic_engine/game/sprites/collectible_sprite.py
fantomatic_engine/game/sprites/decor_sprite.py
fantomatic_engine/game/sprites/interactable_object.py
fantomatic_engine/game/sprites/life_bonus.py
fantomatic_engine/generic/__init__.py
fantomatic_engine/generic/dialog_box.py
fantomatic_engine/generic/loading_window.py
fantomatic_engine/generic/numbers.py
fantomatic_engine/generic/resources_manager.py
fantomatic_engine/generic/sprite.py
fantomatic_engine/generic/vectors.py
fantomatic_engine/generic/automation/__init__.py
fantomatic_engine/generic/automation/bot_sprite.py
fantomatic_engine/generic/control/__init__.py
fantomatic_engine/generic/control/controllable.py
fantomatic_engine/generic/control/inputs/__init__.py
fantomatic_engine/generic/control/inputs/quadridirectional_input.py
fantomatic_engine/generic/events/__init__.py
fantomatic_engine/generic/events/any_listener.py
fantomatic_engine/generic/events/event_listener.py
fantomatic_engine/generic/events/events_handler.py
fantomatic_engine/generic/feedback/__init__.py
fantomatic_engine/generic/feedback/feedback.py
fantomatic_engine/generic/feedback/feedbackable.py
fantomatic_engine/generic/image/__init__.py
fantomatic_engine/generic/image/animation.py
fantomatic_engine/generic/light/__init__.py
fantomatic_engine/generic/light/light_halo.py
fantomatic_engine/generic/menu/__init__.py
fantomatic_engine-0.1.16.dist-info/LICENSE
fantomatic_engine-0.1.16.dist-info/METADATA
fantomatic_engine-0.1.16.dist-info/WHEEL
fantomatic_engine-0.1.16.dist-info/top_level.txt
fantomatic_engine-0.1.16.dist-info/RECORD
