Metadata-Version: 2.1
Name: fantomatic-engine
Version: 0.1.16
Summary: A 2D top viewed game engine based on pygame
Home-page: https://gitlab.com/kuadrado-software/fantomatic-engine
Author: Kuadrado Software
Author-email: contact@kuadrado-software.fr
License: GNU-GPL-3.0
Keywords: game 2d engine videogame
Platform: UNKNOWN
Requires-Python: >=3.9
License-File: LICENSE
Requires-Dist: pygame (==2.1.0)
Requires-Dist: numpy (>=1.19.4)
